Metadata-Version: 1.1
Name: search-file
Version: 1.2.3
Summary: A python module that supplies tools to search files(or directories).一个用于搜索文件或文件夹的Python模块。
Home-page: https://github.com/qfcy/Python/blob/main/search_file.py
Author: 七分诚意 qq:3076711200
Author-email: 3076711200@qq.com
License: UNKNOWN
Keywords: path,search,file,directories,automation
Platform: UNKNOWN
Classifier: Programming Language :: Python
Classifier: Topic :: System :: Filesystems
Classifier: Topic :: Software Development :: Libraries
Classifier: Natural Language :: Chinese (Simplified)
